dockerfile_bakery/__init__.py
dockerfile_bakery/about.py
dockerfile_bakery/cli.py
dockerfile_bakery/dockerfile_assembler.py
dockerfile_bakery/utils/__init__.py
dockerfile_bakery/utils/console.py
dockerfile_bakery-0.1.0.dist-info/METADATA
dockerfile_bakery-0.1.0.dist-info/WHEEL
dockerfile_bakery-0.1.0.dist-info/entry_points.txt
dockerfile_bakery-0.1.0.dist-info/top_level.txt
dockerfile_bakery-0.1.0.dist-info/RECORD
