Metadata-Version: 2.1
Name: dockerfile-bakery
Version: 0.1.0
Summary: Generate Dockerfiles from Partial Dockerfiles
Home-page: https://github.com/kujyp/dockerfile_bakery
Author: kujyp
Author-email: pjo901018@gmail.com
License: UNKNOWN
Platform: UNKNOWN
Requires-Dist: Click (>=7.0)
Requires-Dist: Jinja2 (>=2.10)
